radqy/4d.py
radqy/CT_TAGS.yaml
radqy/MRI_TAGS.yaml
radqy/__init__.py
radqy/cli.py
radqy/radqy.py
radqy/ui_handlers.py
radqy-2025.3.2.dist-info/METADATA
radqy-2025.3.2.dist-info/WHEEL
radqy-2025.3.2.dist-info/entry_points.txt
radqy-2025.3.2.dist-info/top_level.txt
radqy-2025.3.2.dist-info/RECORD
